aspose_imaging_cloud-25.4.0.data/data/LICENSE
asposeimagingcloud/__init__.py
asposeimagingcloud/api_client.py
asposeimagingcloud/configuration.py
asposeimagingcloud/rest.py
asposeimagingcloud/api/__init__.py
asposeimagingcloud/api/imaging_api.py
asposeimagingcloud/models/__init__.py
asposeimagingcloud/models/available_labels_list.py
asposeimagingcloud/models/big_rectangular_filter_properties.py
asposeimagingcloud/models/bilateral_smoothing_filter_properties.py
asposeimagingcloud/models/bmp_properties.py
asposeimagingcloud/models/convolution_filter_properties.py
asposeimagingcloud/models/deconvolution_filter_properties.py
asposeimagingcloud/models/detected_object.py
asposeimagingcloud/models/detected_object_list.py
asposeimagingcloud/models/dicom_properties.py
asposeimagingcloud/models/disc_usage.py
asposeimagingcloud/models/djvu_properties.py
asposeimagingcloud/models/dng_properties.py
asposeimagingcloud/models/eps_properties.py
asposeimagingcloud/models/error.py
asposeimagingcloud/models/error_details.py
asposeimagingcloud/models/exif_data.py
asposeimagingcloud/models/file_version.py
asposeimagingcloud/models/file_versions.py
asposeimagingcloud/models/files_list.py
asposeimagingcloud/models/files_upload_result.py
asposeimagingcloud/models/filter_properties_base.py
asposeimagingcloud/models/gauss_wiener_filter_properties.py
asposeimagingcloud/models/gaussian_blur_filter_properties.py
asposeimagingcloud/models/gif_properties.py
asposeimagingcloud/models/image_duplicates.py
asposeimagingcloud/models/image_duplicates_set.py
asposeimagingcloud/models/image_features.py
asposeimagingcloud/models/imaging_response.py
asposeimagingcloud/models/jfif_data.py
asposeimagingcloud/models/jpeg2000_properties.py
asposeimagingcloud/models/jpeg_exif_data.py
asposeimagingcloud/models/jpeg_properties.py
asposeimagingcloud/models/median_filter_properties.py
asposeimagingcloud/models/motion_wiener_filter_properties.py
asposeimagingcloud/models/object_exist.py
aspose_imaging_cloud-25.4.0.dist-info/LICENSE
aspose_imaging_cloud-25.4.0.dist-info/METADATA
aspose_imaging_cloud-25.4.0.dist-info/WHEEL
aspose_imaging_cloud-25.4.0.dist-info/top_level.txt
aspose_imaging_cloud-25.4.0.dist-info/RECORD
