Metadata-Version: 2.1
Name: aspose-imaging-cloud
Version: 25.4.0
Summary: Aspose.Imaging Cloud Python SDK
Home-page: https://products.aspose.cloud/imaging
Author: Sergei Zubov
Author-email: sergei.zubov@aspose.com
License: MIT
Keywords: Aspose,Imaging,Cloud,REST,API,SDK,image,object detection,reverse search,image effects,filters,deskewing,resize,crop,rotate,convert,metadatabmp,dicom,dng,djvu,djv,emf,gif,jpg,jpe,jpeg,jpeg2000,jp2,jpx,jpm,j2k,odg,png,psd,tiff,tif,webp,wmf,cdr,cmx,pdf,svg,otg
Platform: UNKNOWN
Classifier: Development Status :: 5 - Production/Stable
Classifier: Intended Audience :: Developers
Classifier: Topic :: Multimedia :: Graphics
Classifier: License :: OSI Approved :: MIT License
Classifier: Programming Language :: Python :: 2
Classifier: Programming Language :: Python :: 2.7
Classifier: Programming Language :: Python :: 3
Classifier: Programming Language :: Python :: 3.1
Classifier: Programming Language :: Python :: 3.2
Classifier: Programming Language :: Python :: 3.3
Classifier: Programming Language :: Python :: 3.4
Classifier: Programming Language :: Python :: 3.5
Classifier: Programming Language :: Python :: 3.6
Requires-Dist: urllib3 (==1.24.2)
Requires-Dist: openssl (==1.1.1)
Requires-Dist: six (>=1.11)
Requires-Dist: certifi (>=2018.1)
Requires-Dist: python-dateutil (>=2.8)
